{
  "name": "readabilitySHARK",
  "author": "Alexander Trautsch",
  "version": "0.0.1",
  "plugin_type": "rev",
  "linux_libraries": [
    "gradle"
  ],
  "created_collections": [
  ],
  "description": "collect readability information",
  "requires": [
  ],
  "arguments": [
    {
      "name": "plugin_path",
      "required": true,
      "position": 1,
      "type": "install",
      "description": "path to the root folder of the plugin"
    },
    {
      "name": "plugin_path",
      "required": true,
      "position": 1,
      "type": "execute",
      "description": "path to the root folder of the plugin"
    },
    {
      "name": "path",
      "required": true,
      "position": 2,
      "type": "execute",
      "description": "path to the project repository (revision must be set)"
    },
    {
      "name": "revision",
      "required": true,
      "position": 3,
      "type": "execute",
      "description": "revision hash that is processed"
    },
    {
      "name": "repository_url",
      "required": true,
      "position": 4,
      "type": "execute",
      "description": "url of the project"
    },
    {
      "name": "project_name",
      "required": true,
      "position": 5,
      "type": "execute",
      "description": "name of the project"
    },
    {
      "name": "db_hostname",
      "required": true,
      "position": 6,
      "type": "execute",
      "description": "hostname of the server, where the mongodb runs on"
    },
    {
      "name": "db_port",
      "required": true,
      "position": 7,
      "type": "execute",
      "description": "port on which the mongodb is listening on"
    },
    {
      "name": "db_database",
      "required": true,
      "position": 8,
      "type": "execute",
      "description": "name of the database in the mongodb"
    },
    {
      "name": "db_user",
      "required": false,
      "position": 9,
      "type": "execute",
      "description": "database user for the mongodb"
    },
    {
      "name": "db_password",
      "required": false,
      "position": 10,
      "type": "execute",
      "description": "password for the user of the mongodb"
    },
    {
      "name": "db_authentication",
      "required": false,
      "position": 11,
      "type": "execute",
      "description": "databse against which users are authenticated"
    },
    {
      "name": "ssl_enabled",
      "required": false,
      "position": 12,
      "type": "execute",
      "description": "needs to be set if database uses ssl connection"
    },
    {
      "name": "log_level",
      "required": false,
      "position": 13,
      "type": "execute",
      "description": "debug choices (INFO, DEBUG, WARNING, ERROR)"
    }
  ]
}